{
  "nextID": 11,
  "data": [
    {
      "id": 1,
      "titleCourse": "Como Criar Cursos Online de Sucesso 2024 - 3 Cursos em 1",
      "salesQuantity": 1064,
      "timestamp": "6/15/2024, 11:16:32 AM"
    },
    {
      "id": 2,
      "titleCourse": "Como Criar Cursos Online de Sucesso 2024 - 3 Cursos em 1",
      "salesQuantity": 1065,
      "timestamp": "6/20/2024, 4:50:38 AM",
      "salesAmount": {
        "newSales": 1,
        "inDays": 4,
        "inHours": 17
      }
    },
    {
      "id": 3,
      "titleCourse": "Como Criar Cursos Online de Sucesso 2024 - 3 Cursos em 1",
      "salesQuantity": 1065,
      "timestamp": "6/20/2024, 12:16:27 PM",
      "salesAmount": {
        "newSales": 0,
        "inDays": 0,
        "inHours": 7
      }
    },
    {
      "id": 4,
      "titleCourse": "Como Criar Cursos Online de Sucesso 2024 - 3 Cursos em 1",
      "salesQuantity": 1066,
      "timestamp": "6/26/2024, 4:40:33 AM",
      "salesAmount": {
        "newSales": 1,
        "inDays": 5,
        "inHours": 16
      }
    },
    {
      "id": 5,
      "titleCourse": "Como Criar Cursos Online de Sucesso 2024 - 3 Cursos em 1",
      "salesQuantity": 1068,
      "timestamp": "6/28/2024, 1:41:58 PM",
      "salesAmount": {
        "newSales": 2,
        "inDays": 2,
        "inHours": 9
      }
    },
    {
      "id": 6,
      "titleCourse": "Como Criar Cursos Online de Sucesso 2024 - 3 Cursos em 1",
      "salesQuantity": 1068,
      "timestamp": "7/2/2024, 5:05:25 AM",
      "salesAmount": {
        "newSales": 0,
        "inDays": 3,
        "inHours": 15
      }
    },
    {
      "id": 7,
      "titleCourse": "Como Criar Cursos Online de Sucesso 2024 - 3 Cursos em 1",
      "salesQuantity": 1069,
      "timestamp": "7/3/2024, 5:54:08 PM",
      "salesAmount": {
        "newSales": 1,
        "inDays": 1,
        "inHours": 12
      }
    },
    {
      "id": 8,
      "titleCourse": "Como Criar Cursos Online de Sucesso 2024 - 3 Cursos em 1",
      "salesQuantity": 1073,
      "timestamp": "7/5/2024, 6:43:46 PM",
      "salesAmount": {
        "newSales": 4,
        "inDays": 2,
        "inHours": 0
      }
    },
    {
      "id": 9,
      "titleCourse": "Como Criar Cursos Online de Sucesso 2024 - 3 Cursos em 1",
      "salesQuantity": 1074,
      "timestamp": "7/9/2024, 8:51:17 AM",
      "salesAmount": {
        "newSales": 1,
        "inDays": 3,
        "inHours": 14
      }
    },
    {
      "id": 10,
      "titleCourse": "Como Criar Cursos Online de Sucesso 2024 - 3 Cursos em 1",
      "salesQuantity": 1075,
      "timestamp": "7/16/2024, 4:57:36 AM",
      "salesAmount": {
        "newSales": 1,
        "inDays": 6,
        "inHours": 20
      }
    }
  ]
}